README.rst
setup.cfg
setup.py
bar/__init__.py
bar/speaker.py
foo_eric_test.egg-info/PKG-INFO
foo_eric_test.egg-info/SOURCES.txt
foo_eric_test.egg-info/dependency_links.txt
foo_eric_test.egg-info/top_level.txt