Metadata-Version: 1.0
Name: foo-eric-test
Version: 1.6.1
Summary: funny foo
Home-page: http://github.com/user/foo
Author: ericchan77
Author-email: 1305584643@qq.com
License: UNKNOWN
Platform: UNKNOWN
